module/__init__.py
module/shmyaks.py
Shmyaks-0.1.dist-info/METADATA
Shmyaks-0.1.dist-info/WHEEL
Shmyaks-0.1.dist-info/top_level.txt
Shmyaks-0.1.dist-info/RECORD
